python_myfatoorah/__init__.py
python_myfatoorah/my_fatoorah.py
python_myfatoorah-0.4.0.dist-info/METADATA
python_myfatoorah-0.4.0.dist-info/WHEEL
python_myfatoorah-0.4.0.dist-info/licenses/LICENSE
python_myfatoorah-0.4.0.dist-info/RECORD
